README.md
setup.py
thailandpost_track/__init__.py
thailandpost_track/constants.py
thailandpost_track/language.py
thailandpost_track/request.py
thailandpost_track/status_code.py
thailandpost_track/thailandpost_track.py
thailandpost_track.egg-info/PKG-INFO
thailandpost_track.egg-info/SOURCES.txt
thailandpost_track.egg-info/dependency_links.txt
thailandpost_track.egg-info/requires.txt
thailandpost_track.egg-info/top_level.txt