Metadata-Version: 2.1
Name: thailandpost-track
Version: 1.0.0
Summary: A Python library for Thailand Post track API
Home-page: https://github.com/sang-sakarin/thailandpost-track
Author: sang_sakarin
Author-email: sang_sakarin@outlook.com
License: sang_sakarin
Keywords: thailandport-track thailandport-track-python
Platform: UNKNOWN
